flyte_spark/SparkImageSpec.py
flyte_spark/__init__.py
flyte_spark/py.typed
flyte_spark/utils.py
flyte_spark/resources/entrypoint.sh
flyte_spark-0.1.0.dist-info/METADATA
flyte_spark-0.1.0.dist-info/WHEEL
flyte_spark-0.1.0.dist-info/RECORD
