Metadata-Version: 2.4
Name: flyte-spark
Version: 0.1.0
Summary: ImageSpec for Spark tasks with ipv6 support
Author-email: Julian <julian.streibel@freenet.de>
Requires-Python: >=3.10
Requires-Dist: flytekit>=1.15.2
Requires-Dist: flytekitplugins-spark>=1.15.3
Requires-Dist: pathlib>=1.0.1
